<annotation>
	<folder>n02051845</folder>
	<filename>n02051845_8841</filename>
	<source>
		<database>ImageNet database</database>
	</source>
	<size>
		<width>333</width>
		<height>500</height>
		<depth>3</depth>
	</size>
	<segmented>0</segmented>
	<object>
		<name>n02051845</name>
		<pose>Unspecified</pose>
		<truncated>0</truncated>
		<difficult>0</difficult>
		<bndbox>
			<xmin>23</xmin>
			<ymin>186</ymin>
			<xmax>222</xmax>
			<ymax>466</ymax>
		</bndbox>
	</object>
	<object>
		<name>n02051845</name>
		<pose>Unspecified</pose>
		<truncated>0</truncated>
		<difficult>0</difficult>
		<bndbox>
			<xmin>81</xmin>
			<ymin>103</ymin>
			<xmax>256</xmax>
			<ymax>382</ymax>
		</bndbox>
	</object>
	<object>
		<name>n02051845</name>
		<pose>Unspecified</pose>
		<truncated>0</truncated>
		<difficult>0</difficult>
		<bndbox>
			<xmin>136</xmin>
			<ymin>21</ymin>
			<xmax>322</xmax>
			<ymax>292</ymax>
		</bndbox>
	</object>
</annotation>