<annotation>
	<folder>n02403003</folder>
	<filename>n02403003_4569</filename>
	<source>
		<database>ImageNet database</database>
	</source>
	<size>
		<width>375</width>
		<height>500</height>
		<depth>3</depth>
	</size>
	<segmented>0</segmented>
	<object>
		<name>n02403003</name>
		<pose>Unspecified</pose>
		<truncated>0</truncated>
		<difficult>0</difficult>
		<bndbox>
			<xmin>75</xmin>
			<ymin>197</ymin>
			<xmax>220</xmax>
			<ymax>332</ymax>
		</bndbox>
	</object>
	<object>
		<name>n02403003</name>
		<pose>Unspecified</pose>
		<truncated>0</truncated>
		<difficult>0</difficult>
		<bndbox>
			<xmin>11</xmin>
			<ymin>197</ymin>
			<xmax>98</xmax>
			<ymax>301</ymax>
		</bndbox>
	</object>
</annotation>