<annotation>
	<folder>n02437136</folder>
	<filename>n02437136_4774</filename>
	<source>
		<database>ImageNet database</database>
	</source>
	<size>
		<width>500</width>
		<height>334</height>
		<depth>3</depth>
	</size>
	<segmented>0</segmented>
	<object>
		<name>n02437136</name>
		<pose>Unspecified</pose>
		<truncated>0</truncated>
		<difficult>0</difficult>
		<bndbox>
			<xmin>237</xmin>
			<ymin>99</ymin>
			<xmax>499</xmax>
			<ymax>333</ymax>
		</bndbox>
	</object>
	<object>
		<name>n02437136</name>
		<pose>Unspecified</pose>
		<truncated>0</truncated>
		<difficult>0</difficult>
		<bndbox>
			<xmin>110</xmin>
			<ymin>124</ymin>
			<xmax>499</xmax>
			<ymax>331</ymax>
		</bndbox>
	</object>
</annotation>