<annotation>
	<folder>n02131653</folder>
	<filename>n02131653_10015</filename>
	<source>
		<database>ImageNet database</database>
	</source>
	<size>
		<width>500</width>
		<height>213</height>
		<depth>3</depth>
	</size>
	<segmented>0</segmented>
	<object>
		<name>n02131653</name>
		<pose>Unspecified</pose>
		<truncated>0</truncated>
		<difficult>0</difficult>
		<bndbox>
			<xmin>320</xmin>
			<ymin>43</ymin>
			<xmax>486</xmax>
			<ymax>180</ymax>
		</bndbox>
	</object>
	<object>
		<name>n02131653</name>
		<pose>Unspecified</pose>
		<truncated>0</truncated>
		<difficult>0</difficult>
		<bndbox>
			<xmin>16</xmin>
			<ymin>56</ymin>
			<xmax>132</xmax>
			<ymax>189</ymax>
		</bndbox>
	</object>
	<object>
		<name>n02131653</name>
		<pose>Unspecified</pose>
		<truncated>0</truncated>
		<difficult>0</difficult>
		<bndbox>
			<xmin>136</xmin>
			<ymin>51</ymin>
			<xmax>361</xmax>
			<ymax>187</ymax>
		</bndbox>
	</object>
</annotation>