<annotation>
	<folder>n02508021</folder>
	<filename>n02508021_1628</filename>
	<source>
		<database>ImageNet database</database>
	</source>
	<size>
		<width>500</width>
		<height>375</height>
		<depth>3</depth>
	</size>
	<segmented>0</segmented>
	<object>
		<name>n02508021</name>
		<pose>Unspecified</pose>
		<truncated>0</truncated>
		<difficult>0</difficult>
		<bndbox>
			<xmin>201</xmin>
			<ymin>164</ymin>
			<xmax>336</xmax>
			<ymax>302</ymax>
		</bndbox>
	</object>
	<object>
		<name>n02508021</name>
		<pose>Unspecified</pose>
		<truncated>0</truncated>
		<difficult>0</difficult>
		<bndbox>
			<xmin>189</xmin>
			<ymin>117</ymin>
			<xmax>303</xmax>
			<ymax>192</ymax>
		</bndbox>
	</object>
	<object>
		<name>n02508021</name>
		<pose>Unspecified</pose>
		<truncated>0</truncated>
		<difficult>0</difficult>
		<bndbox>
			<xmin>291</xmin>
			<ymin>208</ymin>
			<xmax>354</xmax>
			<ymax>306</ymax>
		</bndbox>
	</object>
	<object>
		<name>n02508021</name>
		<pose>Unspecified</pose>
		<truncated>0</truncated>
		<difficult>0</difficult>
		<bndbox>
			<xmin>344</xmin>
			<ymin>249</ymin>
			<xmax>435</xmax>
			<ymax>308</ymax>
		</bndbox>
	</object>
</annotation>